{
  "description": "项目配置文件。",
  "packOptions": {
    "ignore": []
  },
  "setting": {
    "urlCheck": false,
    "es6": true,
    "postcss": true,
    "minified": true,
    "newFeature": true,
    "coverView": true,
    "autoAudits": false,
    "showShadowRootInWxmlPanel": true,
    "scopeDataCheck": false,
    "checkInvalidKey": true,
    "checkSiteMap": true,
    "uploadWithSourceMap": true,
    "useMultiFrameRuntime": true,
    "useApiHook": true,
    "babelSetting": {
      "ignore": [],
      "disablePlugins": [],
      "outputPath": ""
    },
    "bundle": false,
    "useIsolateContext": true,
    "useCompilerModule": false,
    "userConfirmedUseCompilerModuleSwitch": false,
    "userConfirmedBundleSwitch": false,
    "packNpmManually": false,
    "packNpmRelationList": [],
    "minifyWXSS": true,
    "useApiHostProcess": false
  },
  "compileType": "miniprogram",
  "libVersion": "2.6.1",
  "appid": "wxe797c3a08d38fbed",
  "projectname": "sunshop",
  "isGameTourist": false,
  "simulatorType": "wechat",
  "simulatorPluginLibVersion": {},
  "condition": {
    "search": {
      "list": []
    },
    "conversation": {
      "list": []
    },
    "game": {
      "currentL": -1,
      "list": []
    },
    "miniprogram": {
      "list": []
    }
  }
}